sjtu_automata/__init__.py
sjtu_automata/__version__.py
sjtu_automata/autocaptcha.py
sjtu_automata/autoelect.py
sjtu_automata/credential.py
sjtu_automata/electsys/__init__.py
sjtu_automata/electsys/automata.py
sjtu_automata/utils/__init__.py
sjtu_automata/utils/exceptions.py
sjtu_automata-0.4.0.dist-info/LICENSE
sjtu_automata-0.4.0.dist-info/METADATA
sjtu_automata-0.4.0.dist-info/WHEEL
sjtu_automata-0.4.0.dist-info/entry_points.txt
sjtu_automata-0.4.0.dist-info/top_level.txt
sjtu_automata-0.4.0.dist-info/RECORD
