Metadata-Version: 2.1
Name: sjtu-automata
Version: 0.4.0
Summary: Auto elect script for SJTUer.
Home-page: https://github.com/MXWXZ/sjtu-automata
Author: MXWXZ
Author-email: me@imwxz.com
License: GNU General Public License v3 (GPLv3)
Platform: UNKNOWN
Classifier: Programming Language :: Python :: 3
Classifier: License :: OSI Approved :: GNU General Public License v3 (GPLv3)
Classifier: Operating System :: OS Independent
Requires-Python: >=3
Requires-Dist: colorama
Requires-Dist: requests
Requires-Dist: Pillow
Requires-Dist: click (>=7.0)
Requires-Dist: pytesseract
Requires-Dist: tenacity
